README
setup.py
marlib/__init__.py
marlib/audiofile.py
marlib/matlab.py
marlib/signal.py
marlib/tests.py
marlib/timefreq.py
marlib/utils.py
marlib.egg-info/PKG-INFO
marlib.egg-info/SOURCES.txt
marlib.egg-info/dependency_links.txt
marlib.egg-info/requires.txt
marlib.egg-info/top_level.txt