Metadata-Version: 1.0
Name: marlib
Version: 0.3.7
Summary: Music Signal Processing and Analysis Library
Home-page: https://bitbucket.org/ejh333/marlib
Author: Eric Humphrey
Author-email: ejhumphrey@nyu.edu
License: LGPL
Download-URL: http://pypi.python.org/packages/source/m/marlib/marlib-0.3.7.tar.gz
Platform: UNKNOWN
